mailparser_reply/__init__.py
mailparser_reply/constants.py
mailparser_reply/parser.py
mailparser_reply/version.py
mail_parser_reply-1.35.dist-info/LICENSE
mail_parser_reply-1.35.dist-info/METADATA
mail_parser_reply-1.35.dist-info/WHEEL
mail_parser_reply-1.35.dist-info/top_level.txt
mail_parser_reply-1.35.dist-info/RECORD
