Metadata-Version: 2.1
Name: mail-parser-reply
Version: 1.35
Summary: 📧 Email reply parser library for Python with multi-language support
Home-page: https://github.com/alfonsrv/mail-parser-reply
Author: Alfons R.
Author-email: alfonsrv@protonmail.com
Maintainer: Alfons R.
Maintainer-email: alfonsrv@protonmail.com
License: MIT
Keywords: mail,email,parser
Classifier: Intended Audience :: Developers
Classifier: Operating System :: OS Independent
Classifier: License :: OSI Approved :: MIT License
Classifier: Programming Language :: Python
Classifier: Programming Language :: Python :: 3
Classifier: Topic :: Software Development
License-File: LICENSE
